gitoo/__init__.py
gitoo/cli.py
gitoo/core.py
gitoo-1.8.dist-info/LICENSE
gitoo-1.8.dist-info/METADATA
gitoo-1.8.dist-info/WHEEL
gitoo-1.8.dist-info/entry_points.txt
gitoo-1.8.dist-info/top_level.txt
gitoo-1.8.dist-info/RECORD
