Metadata-Version: 2.1
Name: gitoo
Version: 1.8
Summary: Odoo third party addons installer.
Home-page: https://github.com/numigi/gitoo
Author: numigi
Author-email: contact@numigi.com
License: MIT
Platform: UNKNOWN
Classifier: License :: OSI Approved :: MIT License
Classifier: Programming Language :: Python
Classifier: Programming Language :: Python :: 3
Classifier: Programming Language :: Python :: Implementation :: CPython
License-File: LICENSE
Requires-Dist: gitpython
Requires-Dist: click
Requires-Dist: click-didyoumean
Requires-Dist: crayons
Requires-Dist: click-help-colors
Requires-Dist: pyyaml
Requires-Dist: pystache
